{"bucket":"games","container_type":"product","content_type":"1","default_sku":{"amortizeFlag":false,"bundleExclusiveFlag":false,"chargeImmediatelyFlag":false,"charge_type_id":0,"credit_card_required_flag":0,"defaultSku":true,"display_price":"HK$78.00","eligibilities":[],"entitlements":[{"description":null,"drms":[{"drm_category_type":1,"id":"HP0325-NPHH00057_00-0000000000000000","is_streamable":0,"media_prop":[],"size":299166128,"type":2}],"duration":0,"exp_after_first_use":0,"feature_type_id":0,"id":"HP0325-NPHH00057_00-0000000000000000","license_type":1,"name":"Karakuri (Tokobot\u2122) \u88fd\u54c1\u7248","packageType":null,"packages":[],"preorder_placeholder_flag":false,"size":0,"subType":0,"subtitle_language_codes":null,"type":2,"use_count":0,"voice_language_codes":null}],"id":"HP0325-NPHH00057_00-0000000000000000-H001","is_original":false,"name":"\u65e5\u6587\u7248","platforms":[0,1,10],"price":7800,"rewards":[],"seasonPassExclusiveFlag":false,"skuAvailabilityOverrideFlag":false,"sku_type":0,"type":"standard"},"gameContentTypesList":[{"name":"\u904a\u6232","key":"GAME"}],"game_contentType":"\u904a\u6232","id":"HP0325-NPHH00057_00-0000000000000000","images":[{"type":1,"url":"http:\/\/apollo2.dl.playstation.net\/cdn\/HP0325\/NPHH00057_00\/98L1QXMKi0LVSHF1iykkqRDh1XYyUCRj.png"},{"type":2,"url":"http:\/\/apollo2.dl.playstation.net\/cdn\/HP0325\/NPHH00057_00\/98L1QXMKi0LVSHF1iykkqRDh1XYyUCRj_80.png"},{"type":9,"url":"http:\/\/apollo2.dl.playstation.net\/cdn\/HP0325\/NPHH00057_00\/98L1QXMKi0LVSHF1iykkqRDh1XYyUCRj_160.png"}],"name":"Karakuri (Tokobot\u2122) \u88fd\u54c1\u7248","playable_platform":["PSP\u00ae","PS Vita"],"provider_name":"KOEI TECMO GAMES CO., LTD.","release_date":"2009-11-10T00:00:00Z","restricted":false,"revision":29,"short_name":"Karakuri (Tokobot\u2122) \u88fd\u54c1\u7248","timestamp":1467933034000,"top_category":"downloadable_game","url":"https:\/\/store.playstation.com\/store\/api\/chihiro\/00_09_000\/container\/HK\/ch\/999\/HP0325-NPHH00057_00-0000000000000000?game_content_type=games&platform=vita&size=30&gkb=1&geoCountry=RU&start=0","expanded":true,"age_limit":0,"content_origin":0,"content_rating":[],"dob_required":false,"legal_text":"\u6240\u8cfc\u8cb7\u7684\u5167\u5bb9\u6216\u670d\u52d9\u5747\u4e0d\u53ef\u9000\u6b3e\u6216\u8f49\u8b93\uff0c\u4ea6\u4e0d\u53ef\u7528\u4ee5\u8d16\u56de\u73fe\u91d1\u6216\u8a18\u8cec\u3002","links":[],"long_desc":"\u626e\u6f14\u601d\u7dad\u654f\u6377\u7684\u7279\u5de5Bolt\uff0c\u96c6\u5408\u9f4a\u5fc3\u5354\u529b\u5e6b\u52a9\u4f60\u7684\u53ef\u611b\u6a5f\u5668\u4ebaTokobot\u2122\uff0c\u5229\u7528\u5b83\u5011\u7368\u7279\u4e14\u5145\u6eff\u5275\u9020\u6027\u7684\u968a\u5f62\u5e36\u9818\u5b83\u5011\u958b\u59cb\u63a2\u96aa\u5427\uff01\u628a\u6a5f\u5668\u4eba\u7d44\u6210\u87ba\u65cb\u69f3\u4f86\u5e6b\u4f60\u98db\u7fd4\uff0c\u5c07\u5b83\u5011\u758a\u6210\u68af\u5b50\u628a\u4f60\u9001\u5230\u9ad8\u8655\uff0c\u6216\u662f\u628a\u5b83\u5011\u8b8a\u5f62\u6210\u70ba\u7d42\u6975\u5408\u6210\u9ad4\u2014\u2014\u5766\u514b\u3001\u5f48\u5c04\u5668\u9084\u6709\u5176\u4ed6\u66f4\u591a\uff01<br>\u2022\u64cd\u7e31Tokobot\u5275\u9020\u300c\u5718\u968a\u5408\u6210\u9ad4\u300d\uff0c\u7a7f\u8d8a\u5404\u7a2e\u969c\u7919\uff01<br>\u2022\u5728\u904a\u6232\u6700\u521d\u73a9\u8005\u53ea\u67096\u500bTokobot\uff0c\u4f46\u5728\u904a\u6232\u4e2d\u5c07\u6709\u6a5f\u6703\u7372\u5f97\u66f4\u591a\uff01<br>\u2022\u904b\u7528\u7121\u7aae\u7684\u60f3\u50cf\u529b\u5275\u9020\u524d\u6240\u672a\u6709\u7684\u968a\u5f62\uff0c\u5b8c\u6210\u66f4\u5927\u7684\u6311\u6230\uff01<br>\u2022\u5c07Tokobot\u7d44\u5408\u6210\u7d42\u6975\u7684\u5408\u6210\u9ad4\uff0c\u8b93\u5b83\u5011\u8b8a\u6210\u7528\u9014\u5343\u8b8a\u842c\u5316\u7684\u5de8\u5927\u6a5f\u5668\uff0c\u4f8b\u5982\u8d77\u91cd\u6a5f\u3001\u706b\u8eca\u3001\u5766\u514b\u3001\u8eca\u8f2a\uff0c\u9084\u6709\u5176\u4ed6\u66f4\u591a\uff01<br><br><b>\u672c\u5167\u5bb9\u50c5\u80fd\u5728PSP\u00ae (PlayStation\u00aePortable)\u4e0a\u904a\u73a9\u3002<\/b><br><br><b>\u5167\u5bb9\u5bb9\u91cf\uff1a<\/b><br>286MB<br><br><b>Copyright\uff1a<\/b><br>\u00a9 TECMO, LTD. 2005 <br><br>\u55ae\u6b21\u8cfc\u8cb7\u53ef\u65bc\u6700\u591a2\u53f0\u4e3b\u6a5f\u7cfb\u7d71\u53ca2\u53f0\u624b\u63d0\u7cfb\u7d71\u4e0a\u9032\u884c\u4e0b\u8f09\u6216\u5171\u7528\u672c\u5167\u5bb9\uff0c\u6709\u95dc\u7cfb\u7d71\u5fc5\u9808\u8207\u4ed8\u6b3e\u5e33\u6236\u806f\u7e6b\u53ca\u517c\u5bb9\u672c\u5167\u5bb9\u3002<br><br>\u8cfc\u8cb7\u6216\u4f7f\u7528\u672c\u5167\u5bb9\u9700\u9075\u5b88PlayStation\u00aeNetwork\u4f7f\u7528\u689d\u6b3e\u53ca\u7528\u6236\u5408\u7d04\u3002","media_layouts":[{"type":"description","height":1,"width":4}],"metadata":{"game_genre":{"name":"\u985e\u578b","values":["ACTION"]},"playable_platform":{"name":"playable_platform","values":["PSP\u00ae","PS Vita"]},"hiragana":{"name":"hiragana","values":["Karakuri Tokobot full game"]},"tertiary_classification":{"name":"tertiary_classification","values":["NA"]},"container_type":{"name":"\u96c6\u88dd\u985e\u578b","values":["REPRESENTATIVE"]},"genre":{"name":"\u985e\u578b","values":["\u52d5\u4f5c"]},"secondary_classification":{"name":"secondary_classification","values":["GAME"]},"primary_classification":{"name":"primary_classification","values":["PREMIUM_GAME"]}},"pageTypeId":2,"promomedia":[],"size":0,"sku_links":[],"skus":[{"amortizeFlag":false,"bundleExclusiveFlag":false,"chargeImmediatelyFlag":false,"charge_type_id":0,"credit_card_required_flag":0,"defaultSku":true,"display_price":"HK$78.00","eligibilities":[],"entitlements":[{"description":null,"drms":[{"drm_category_type":1,"id":"HP0325-NPHH00057_00-0000000000000000","is_streamable":0,"media_prop":[],"size":299166128,"type":2}],"duration":0,"exp_after_first_use":0,"feature_type_id":0,"id":"HP0325-NPHH00057_00-0000000000000000","license_type":1,"name":"Karakuri (Tokobot\u2122) \u88fd\u54c1\u7248","packageType":null,"packages":[],"preorder_placeholder_flag":false,"size":0,"subType":0,"subtitle_language_codes":null,"type":2,"use_count":0,"voice_language_codes":null}],"id":"HP0325-NPHH00057_00-0000000000000000-H001","is_original":false,"name":"\u65e5\u6587\u7248","platforms":[0,1,10],"price":7800,"rewards":[],"seasonPassExclusiveFlag":false,"skuAvailabilityOverrideFlag":false,"sku_type":0,"type":"standard"}],"star_rating":{"total":"0","score":"0.00","count":null},"start":0,"title_name":"Karakuri (Tokobot\u2122)","total_results":0,"depth":0,"skuFound":true}