{"bucket":"games","container_type":"product","content_type":"1","default_sku":{"amortizeFlag":false,"bundleExclusiveFlag":false,"chargeImmediatelyFlag":false,"charge_type_id":0,"credit_card_required_flag":0,"defaultSku":true,"display_price":"HK$101.00","eligibilities":[],"entitlements":[{"description":null,"drms":[],"duration":0,"exp_after_first_use":0,"feature_type_id":3,"id":"JP0122-CUSA01586_00-0000000000000000","license_type":0,"name":"Croixleur Sigma","packageType":"PS4GD","packages":[{"platformId":13,"platformName":"ps4","size":1119420416}],"preorder_placeholder_flag":false,"size":0,"subType":0,"subtitle_language_codes":null,"type":5,"use_count":0,"voice_language_codes":null},{"description":null,"drms":[{"drm_category_type":5,"id":"JP0122-PCSG00537_00-CROIXLEUR0000000","is_streamable":0,"media_prop":[],"size":791586384,"type":2}],"duration":0,"exp_after_first_use":0,"feature_type_id":0,"id":"JP0122-PCSG00537_00-CROIXLEUR0000000","license_type":1,"name":"Croixleur Sigma","packageType":null,"packages":[],"preorder_placeholder_flag":false,"size":0,"subType":0,"subtitle_language_codes":null,"type":2,"use_count":0,"voice_language_codes":null}],"id":"JP0122-PCSG00537_00-ASIACROIXLEUR000-H001","is_original":false,"name":"\u65e5\u6587\u7248","platforms":[0,1,10],"price":10100,"rewards":[],"seasonPassExclusiveFlag":false,"skuAvailabilityOverrideFlag":false,"sku_type":0,"type":"standard"},"gameContentTypesList":[{"name":"\u904a\u6232","key":"GAME"}],"game_contentType":"\u904a\u6232","id":"JP0122-PCSG00537_00-ASIACROIXLEUR000","images":[{"type":1,"url":"http:\/\/apollo2.dl.playstation.net\/cdn\/JP0122\/PCSG00537_00\/93gP3i2Dm7nhskLYCCxCMqgUgd6I0jnsYXiXMG5ug3iQuRStv3myRUEeZYDu5njw.png"},{"type":2,"url":"http:\/\/apollo2.dl.playstation.net\/cdn\/JP0122\/PCSG00537_00\/0NmvAYufXhqCX5zQLhqFUKZKJxjKM6w06BkPgXGrvEVOJDqveShXCak0ljtH0Do3.png"},{"type":9,"url":"http:\/\/apollo2.dl.playstation.net\/cdn\/JP0122\/PCSG00537_00\/pFs0OXN1BVHjPFohmqiJWwEDRdwZRlDGXGY1gWTmK0IqYfLreQwAY0C3Ap9nqjY6.png"},{"type":10,"url":"http:\/\/apollo2.dl.playstation.net\/cdn\/JP0122\/PCSG00537_00\/MaJCWnFMU29nBUFuy5cGyOKcbTHf7O5r2xDcpbMesBSK6bS2fJiPtbwHmBQCtKWP.png"}],"name":"Croixleur Sigma","playable_platform":["PS Vita"],"provider_name":"PLAYISM","release_date":"2016-03-28T01:00:00Z","restricted":false,"revision":2,"short_name":"Croixleur Sigma","timestamp":1468053649000,"top_category":"downloadable_game","url":"https:\/\/store.playstation.com\/store\/api\/chihiro\/00_09_000\/container\/HK\/ch\/999\/JP0122-PCSG00537_00-ASIACROIXLEUR000?game_content_type=games&platform=vita&size=30&gkb=1&geoCountry=RU&start=0","expanded":true,"age_limit":0,"content_origin":0,"content_rating":[],"dob_required":false,"links":[],"long_desc":"<font color=\"orange\"><b>\u203b\u6b64\u5546\u54c1\u9664PlayStation\u00aeVita\u7528\u5167\u5bb9\u5916\uff0c\u4ea6\u5305\u542b\u9069\u7528\u65bcPlayStation\u00ae4\u4e4b\u5167\u5bb9\u3002\u95dc\u65bcPlayStation\u00ae4\u5167\u5bb9\u7684\u8a73\u7d30\u8cc7\u8a0a\uff0c\u8acb\u65bcPlayStation\u00aeStore\u78ba\u8a8d\u3002<\/b><\/font><br><br>4\u540d\u5c11\u5973\u904b\u7528\u9b54\u6cd5\u528d\u628a\u63a5\u9023\u51fa\u73fe\u7684\u602a\u7269\u4e00\u6383\u800c\u7a7a\uff0c\u723d\u5feb\u611f\u51fa\u773e\u7684\u8d85\u5f37\u52d5\u4f5c\u904a\u6232\uff01\u5404\u4e0d\u76f8\u540c\u7684\u6230\u9b25\u98a8\u683c\u642d\u914d4\u7a2e\u6b66\u5668\uff0c\u4eab\u53d7\u81ea\u5df1\u7279\u6709\u7684\u6230\u9b25\u65b9\u5f0f\u3002\u4ee5\u5c11\u5973\u5011\u7684\u9583\u4eae\u53cb\u60c5\u6545\u4e8b\u70ba\u4e3b\u8ef8\u63a8\u9032\u7684Story Mode\uff08\u6545\u4e8b\u6a21\u5f0f\uff09\u70ba\u5168\u65e5\u8a9e\u914d\u97f3\uff01\u4e5f\u53ef\u76e1\u60c5\u73a9\u904dScore Attack Mode\uff08\u6436\u5206\u6a21\u5f0f\uff09\u3001Challenge Mode\uff08\u6311\u6230\u6a21\u5f0f\uff09\u6216\u63a5\u9023\u8b8a\u63db\u6b66\u5668\u7684Dungeon Mode\uff08\u5730\u4e0b\u57ce\u6a21\u5f0f\uff09\u7b49\u591a\u7a2e\u6a21\u5f0f\uff01\u88dd\u5099\u5404\u7a2e\u4e00\u73a9\u518d\u73a9\u7684\u8981\u7d20\uff01\u5229\u7528Cat Ear\uff08\u8c93\u8033\uff09\u3001Spectacle\uff08\u773c\u93e1\uff09\u3001Headphone\uff08\u8033\u6a5f\uff09\u7b49\u914d\u4ef6\u66ff\u5c11\u5973\u76db\u88dd\u6253\u626e\uff0c\u7136\u5f8c\u4f7f\u51fa\u6280\u80fd\u8fce\u6230\u5427\uff01<br>\u5ba2\u6236\u670d\u52d9<br>PLAYISM: http:\/\/www.playism.jp<br>mail: support@cs.playism.jp<br><br><b>Copyright\uff1a<\/b><br>\u00a9 souvenir circ. All Rights Reserved. \u00a9 Active Gaming Media Inc. All Rights Reserved.<br>PLAYISM, the PLAYISM logo and other related images are registered trademarks of Active Gaming Media Inc.<br><br>\u8cfc\u8cb7\u6216\u4f7f\u7528\u672c\u5167\u5bb9\u9700\u9075\u5b88SEN\u4f7f\u7528\u689d\u6b3e\u53ca\u7528\u6236\u5408\u7d04\u3002","media_layouts":[{"type":"screenshots","height":1,"width":1},{"type":"description","height":1,"width":3}],"metadata":{"game_genre":{"name":"\u985e\u578b","values":["ACTION"]},"playable_platform":{"name":"playable_platform","values":["PS Vita"]},"hiragana":{"name":"hiragana","values":["Croixleur Sigma"]},"tertiary_classification":{"name":"tertiary_classification","values":["NA"]},"container_type":{"name":"\u96c6\u88dd\u985e\u578b","values":["REPRESENTATIVE"]},"genre":{"name":"\u985e\u578b","values":["\u52d5\u4f5c"]},"secondary_classification":{"name":"secondary_classification","values":["GAME"]},"primary_classification":{"name":"primary_classification","values":["DOWNLOADABLE_GAME"]}},"pageTypeId":2,"promomedia":[{"anno":"","id":8193,"key":"space","materials":[{"anno":"","countries":[{"agelimit":0,"uagelimit":0,"country":"cn"},{"agelimit":0,"uagelimit":0,"country":"hk"},{"agelimit":0,"uagelimit":0,"country":"id"},{"agelimit":0,"uagelimit":0,"country":"kr"},{"agelimit":0,"uagelimit":0,"country":"my"},{"agelimit":0,"uagelimit":0,"country":"sg"},{"agelimit":0,"uagelimit":0,"country":"th"},{"agelimit":0,"uagelimit":0,"country":"tw"}],"from":"2016-03-22T00:00:00.000Z","id":400031874,"lang":["1","9","11","10"],"lastm":"2016-03-22T06:08:40.000Z","until":"2100-12-31T00:00:00.000Z","urls":[{"type":25,"url":"https:\/\/nsx.np.dl.playstation.net\/nsx\/material\/7\/72d33c0877e93c10fb325af3b3c03eabfea719e6-1122144.png"}]},{"anno":"","countries":[{"agelimit":0,"uagelimit":0,"country":"cn"},{"agelimit":0,"uagelimit":0,"country":"hk"},{"agelimit":0,"uagelimit":0,"country":"id"},{"agelimit":0,"uagelimit":0,"country":"kr"},{"agelimit":0,"uagelimit":0,"country":"my"},{"agelimit":0,"uagelimit":0,"country":"sg"},{"agelimit":0,"uagelimit":0,"country":"th"},{"agelimit":0,"uagelimit":0,"country":"tw"}],"from":"2016-03-22T00:00:00.000Z","id":400031876,"lang":["1","9","11","10"],"lastm":"2016-03-22T06:08:40.000Z","until":"2100-12-31T00:00:00.000Z","urls":[{"type":25,"url":"https:\/\/nsx.np.dl.playstation.net\/nsx\/material\/e\/ef768f16d4904d40ffb26ba97e5ba4f9bb30b992-1122145.png"}]},{"anno":"","countries":[{"agelimit":0,"uagelimit":0,"country":"cn"},{"agelimit":0,"uagelimit":0,"country":"hk"},{"agelimit":0,"uagelimit":0,"country":"id"},{"agelimit":0,"uagelimit":0,"country":"kr"},{"agelimit":0,"uagelimit":0,"country":"my"},{"agelimit":0,"uagelimit":0,"country":"sg"},{"agelimit":0,"uagelimit":0,"country":"th"},{"agelimit":0,"uagelimit":0,"country":"tw"}],"from":"2016-03-22T00:00:00.000Z","id":400031878,"lang":["1","9","11","10"],"lastm":"2016-03-22T06:08:41.000Z","until":"2100-12-31T00:00:00.000Z","urls":[{"type":25,"url":"https:\/\/nsx.np.dl.playstation.net\/nsx\/material\/e\/eaaa973aff8b39b62483738580c65e38dfc6a6ae-1122146.png"}]}],"multi":"ordered","rep":"t","type":99},{"anno":"","id":8196,"key":"space","materials":[{"anno":"","countries":[{"agelimit":0,"uagelimit":0,"country":"cn"},{"agelimit":0,"uagelimit":0,"country":"hk"},{"agelimit":0,"uagelimit":0,"country":"id"},{"agelimit":0,"uagelimit":0,"country":"kr"},{"agelimit":0,"uagelimit":0,"country":"my"},{"agelimit":0,"uagelimit":0,"country":"sg"},{"agelimit":0,"uagelimit":0,"country":"th"},{"agelimit":0,"uagelimit":0,"country":"tw"}],"from":"2016-03-22T00:00:00.000Z","id":400031875,"lang":["1","9","11","10"],"lastm":"2016-03-22T06:08:40.000Z","until":"2100-12-31T00:00:00.000Z","urls":[{"type":132,"url":"https:\/\/nsx.np.dl.playstation.net\/nsx\/material\/7\/72d33c0877e93c10fb325af3b3c03eabfea719e6-1122147.png"}]},{"anno":"","countries":[{"agelimit":0,"uagelimit":0,"country":"cn"},{"agelimit":0,"uagelimit":0,"country":"hk"},{"agelimit":0,"uagelimit":0,"country":"id"},{"agelimit":0,"uagelimit":0,"country":"kr"},{"agelimit":0,"uagelimit":0,"country":"my"},{"agelimit":0,"uagelimit":0,"country":"sg"},{"agelimit":0,"uagelimit":0,"country":"th"},{"agelimit":0,"uagelimit":0,"country":"tw"}],"from":"2016-03-22T00:00:00.000Z","id":400031877,"lang":["1","9","11","10"],"lastm":"2016-03-22T06:08:41.000Z","until":"2100-12-31T00:00:00.000Z","urls":[{"type":132,"url":"https:\/\/nsx.np.dl.playstation.net\/nsx\/material\/e\/ef768f16d4904d40ffb26ba97e5ba4f9bb30b992-1122148.png"}]},{"anno":"","countries":[{"agelimit":0,"uagelimit":0,"country":"cn"},{"agelimit":0,"uagelimit":0,"country":"hk"},{"agelimit":0,"uagelimit":0,"country":"id"},{"agelimit":0,"uagelimit":0,"country":"kr"},{"agelimit":0,"uagelimit":0,"country":"my"},{"agelimit":0,"uagelimit":0,"country":"sg"},{"agelimit":0,"uagelimit":0,"country":"th"},{"agelimit":0,"uagelimit":0,"country":"tw"}],"from":"2016-03-22T00:00:00.000Z","id":400031879,"lang":["1","9","11","10"],"lastm":"2016-03-22T06:08:41.000Z","until":"2100-12-31T00:00:00.000Z","urls":[{"type":132,"url":"https:\/\/nsx.np.dl.playstation.net\/nsx\/material\/e\/eaaa973aff8b39b62483738580c65e38dfc6a6ae-1122149.png"}]}],"multi":"ordered","rep":"t","type":99}],"size":0,"sku_links":[],"skus":[{"amortizeFlag":false,"bundleExclusiveFlag":false,"chargeImmediatelyFlag":false,"charge_type_id":0,"credit_card_required_flag":0,"defaultSku":true,"display_price":"HK$101.00","eligibilities":[],"entitlements":[{"description":null,"drms":[],"duration":0,"exp_after_first_use":0,"feature_type_id":3,"id":"JP0122-CUSA01586_00-0000000000000000","license_type":0,"name":"Croixleur Sigma","packageType":"PS4GD","packages":[{"platformId":13,"platformName":"ps4","size":1119420416}],"preorder_placeholder_flag":false,"size":0,"subType":0,"subtitle_language_codes":null,"type":5,"use_count":0,"voice_language_codes":null},{"description":null,"drms":[{"drm_category_type":5,"id":"JP0122-PCSG00537_00-CROIXLEUR0000000","is_streamable":0,"media_prop":[],"size":791586384,"type":2}],"duration":0,"exp_after_first_use":0,"feature_type_id":0,"id":"JP0122-PCSG00537_00-CROIXLEUR0000000","license_type":1,"name":"Croixleur Sigma","packageType":null,"packages":[],"preorder_placeholder_flag":false,"size":0,"subType":0,"subtitle_language_codes":null,"type":2,"use_count":0,"voice_language_codes":null}],"id":"JP0122-PCSG00537_00-ASIACROIXLEUR000-H001","is_original":false,"name":"\u65e5\u6587\u7248","platforms":[0,1,10],"price":10100,"rewards":[],"seasonPassExclusiveFlag":false,"skuAvailabilityOverrideFlag":false,"sku_type":0,"type":"standard"}],"star_rating":{"total":"14","score":"4.57","count":[{"star":4,"count":6},{"star":5,"count":8}]},"start":0,"title_name":"Croixleur Sigma","total_results":0,"depth":0,"skuFound":true}