{"bucket":"games","container_type":"product","content_type":"1","default_sku":{"amortizeFlag":false,"bundleExclusiveFlag":false,"chargeImmediatelyFlag":false,"charge_type_id":0,"credit_card_required_flag":0,"defaultSku":true,"display_price":"$9.99","eligibilities":[],"entitlements":[{"description":null,"drms":[{"drm_category_type":5,"id":"UP0082-NPUH10125_00-FINALFANTASY3PSP","is_streamable":0,"media_prop":[],"size":243359920,"type":2}],"duration":0,"exp_after_first_use":0,"feature_type_id":0,"id":"UP0082-NPUH10125_00-FINALFANTASY3PSP","license_type":1,"name":"FINAL FANTASY\u00ae III","packageType":null,"packages":[],"preorder_placeholder_flag":false,"size":0,"subType":0,"subtitle_language_codes":null,"type":2,"use_count":0,"voice_language_codes":null}],"id":"UP0082-NPUH10125_00-FINALFANTASY3PSP-U003","is_original":false,"name":"233 MB Required","platforms":[0,1,10],"price":999,"rewards":[],"seasonPassExclusiveFlag":false,"skuAvailabilityOverrideFlag":false,"sku_type":0,"type":"standard"},"gameContentTypesList":[{"name":"Game","key":"GAME"}],"game_contentType":"Game","id":"UP0082-NPUH10125_00-FINALFANTASY3PSP","images":[{"type":1,"url":"http:\/\/apollo2.dl.playstation.net\/cdn\/UP0082\/NPUH10125_00\/9RpINOQbhX8ir1uuwen0LeKXRQC58KQy.png"},{"type":2,"url":"http:\/\/apollo2.dl.playstation.net\/cdn\/UP0082\/NPUH10125_00\/i7AgIlnEk7hyCqyWVRoGyBDkcjaT8B9m.png"},{"type":9,"url":"http:\/\/apollo2.dl.playstation.net\/cdn\/UP0082\/NPUH10125_00\/Mn6yFP4rcvT5rb3DYBM1LbobrHWRAYlV.png"},{"type":10,"url":"http:\/\/apollo2.dl.playstation.net\/cdn\/UP0082\/NPUH10125_00\/iaXze5TGB1gs14nPyPx8iMRLUvkeFaDl.png"}],"name":"FINAL FANTASY\u00ae III","playable_platform":["PSP","PS Vita"],"provider_name":"SQUARE ENIX CO. LTD.","release_date":"2012-09-25T00:00:00Z","restricted":false,"revision":14,"short_name":"FINAL FANTASY\u00ae III","timestamp":1470701701000,"top_category":"downloadable_game","url":"https:\/\/store.playstation.com\/store\/api\/chihiro\/00_09_000\/container\/US\/en\/999\/UP0082-NPUH10125_00-FINALFANTASY3PSP?platform=vita&game_content_type=games&size=30&gkb=1&geoCountry=RU&start=0","expanded":true,"age_limit":13,"content_descriptors":[{"description":"Violence","url":null,"name":"Violence"},{"description":"Blood","url":null,"name":"Blood"},{"description":"Partial Nudity","url":null,"name":"Partial Nudity"}],"content_origin":0,"content_rating":{"rating_system":"ESRB","url":"https:\/\/cdn-a.sonyentertainmentnetwork.com\/grc\/images\/ratings\/hd\/esrb\/t.png"},"dob_required":false,"links":[],"long_desc":"First released in 1990, FINAL FANTASY\u00ae III introduced series hallmarks such as the job system and summon spells, and became the first in the series to sell over a million copies. Reborn in full 3D in 2006, this classic installment of the FINAL FANTASY series is now available for the PSP\u00ae (PlayStation\u00aePortable) system! Graphics have been re-adjusted to fit the 16:9 aspect ratio, and new features such as the sound and image gallery, an option to switch to the original BGM and an 'auto-battle' system that doubles the speed of combat, have been added!<br><br>  Software subject to license (us.playstation.com\/softwarelicense).\u00a0 Online activity subject to Terms of Services and User Agreement (www.sonyenteretainmentnetwork.com\/terms-of-service).<br><br>\u00a9 1990 - 2012 SQUARE ENIX CO., LTD. All Rights Reserved. <br>TITLE DESIGN: Yoshitaka Amano. CHARACTER DESIGN: Akihiko Yoshida. FINAL FANTASY, SQUARE ENIX, and the SQUARE ENIX logo are registered trademarks or trademarks of Square Enix Co., Ltd.","media_layouts":[{"type":"screenshots","height":1,"width":1},{"type":"description","height":1,"width":3}],"metadata":{"game_genre":{"name":"Genre","values":["ROLE_PLAYING_GAMES"]},"playable_platform":{"name":"playable_platform","values":["PSP","PS Vita"]},"subgenre":{"name":"subgenre","values":["FANTASY"]},"container_type":{"name":"Container Type","values":["REPRESENTATIVE"]},"genre":{"name":"Genre","values":["Role-Playing Games (RPG)"]},"secondary_classification":{"name":"secondary_classification","values":["GAME"]},"game_subgenre":{"name":"subgenre","values":["FANTASY"]},"primary_classification":{"name":"primary_classification","values":["PREMIUM_GAME"]}},"pageTypeId":2,"promomedia":[{"anno":"","id":8193,"key":"space","materials":[{"anno":"","countries":[{"agelimit":10,"uagelimit":0,"country":"br"},{"agelimit":10,"uagelimit":0,"country":"ca"},{"agelimit":10,"uagelimit":0,"country":"mx"},{"agelimit":10,"uagelimit":0,"country":"us"}],"from":"2012-09-19T00:00:00.000Z","id":1080555780,"lang":["all"],"lastm":"2012-09-19T23:44:43.000Z","until":"2100-12-31T23:59:00.000Z","urls":[{"type":26,"url":"https:\/\/nsx.np.dl.playstation.net\/nsx\/material\/5\/5290393e0c20518299d38cf48f9c0f1488a2e1e1-281330.jpg"}]},{"anno":"","countries":[{"agelimit":10,"uagelimit":0,"country":"br"},{"agelimit":10,"uagelimit":0,"country":"ca"},{"agelimit":10,"uagelimit":0,"country":"mx"},{"agelimit":10,"uagelimit":0,"country":"us"}],"from":"2012-09-19T00:00:00.000Z","id":1080555779,"lang":["all"],"lastm":"2012-09-19T23:44:18.000Z","until":"2100-12-31T23:59:00.000Z","urls":[{"type":26,"url":"https:\/\/nsx.np.dl.playstation.net\/nsx\/material\/9\/9225cc0d2cdd800463aa131d32aa100456c6b404-281316.jpg"}]},{"anno":"","countries":[{"agelimit":10,"uagelimit":0,"country":"br"},{"agelimit":10,"uagelimit":0,"country":"ca"},{"agelimit":10,"uagelimit":0,"country":"mx"},{"agelimit":10,"uagelimit":0,"country":"us"}],"from":"2012-09-19T00:00:00.000Z","id":1080555778,"lang":["all"],"lastm":"2012-09-19T23:43:46.000Z","until":"2100-12-31T23:59:00.000Z","urls":[{"type":26,"url":"https:\/\/nsx.np.dl.playstation.net\/nsx\/material\/1\/157a9061f5687436dc2cb8de307389ba010b4517-281315.jpg"}]},{"anno":"","countries":[{"agelimit":10,"uagelimit":0,"country":"br"},{"agelimit":10,"uagelimit":0,"country":"ca"},{"agelimit":10,"uagelimit":0,"country":"mx"},{"agelimit":10,"uagelimit":0,"country":"us"}],"from":"2012-09-19T00:00:00.000Z","id":1080555777,"lang":["all"],"lastm":"2012-09-19T23:43:15.000Z","until":"2100-12-31T23:59:00.000Z","urls":[{"type":26,"url":"https:\/\/nsx.np.dl.playstation.net\/nsx\/material\/2\/2fb2539c8f0f932833693ef03374587ed5300e30-281314.jpg"}]},{"anno":"","countries":[{"agelimit":10,"uagelimit":0,"country":"br"},{"agelimit":10,"uagelimit":0,"country":"ca"},{"agelimit":10,"uagelimit":0,"country":"mx"},{"agelimit":10,"uagelimit":0,"country":"us"}],"from":"2012-09-19T00:00:00.000Z","id":1080555776,"lang":["all"],"lastm":"2012-09-19T23:40:57.000Z","until":"2100-12-31T23:59:00.000Z","urls":[{"type":26,"url":"https:\/\/nsx.np.dl.playstation.net\/nsx\/material\/b\/bde9a061e2fc25d1cc8f3be409016b1ed887c212-281313.jpg"}]}],"multi":"ordered","rep":"t","type":99}],"size":0,"sku_links":[],"skus":[{"amortizeFlag":false,"bundleExclusiveFlag":false,"chargeImmediatelyFlag":false,"charge_type_id":0,"credit_card_required_flag":0,"defaultSku":true,"display_price":"$9.99","eligibilities":[],"entitlements":[{"description":null,"drms":[{"drm_category_type":5,"id":"UP0082-NPUH10125_00-FINALFANTASY3PSP","is_streamable":0,"media_prop":[],"size":243359920,"type":2}],"duration":0,"exp_after_first_use":0,"feature_type_id":0,"id":"UP0082-NPUH10125_00-FINALFANTASY3PSP","license_type":1,"name":"FINAL FANTASY\u00ae III","packageType":null,"packages":[],"preorder_placeholder_flag":false,"size":0,"subType":0,"subtitle_language_codes":null,"type":2,"use_count":0,"voice_language_codes":null}],"id":"UP0082-NPUH10125_00-FINALFANTASY3PSP-U003","is_original":false,"name":"233 MB Required","platforms":[0,1,10],"price":999,"rewards":[],"seasonPassExclusiveFlag":false,"skuAvailabilityOverrideFlag":false,"sku_type":0,"type":"standard"}],"star_rating":{"total":"437","score":"4.69","count":[{"star":1,"count":14},{"star":2,"count":1},{"star":3,"count":10},{"star":4,"count":54},{"star":5,"count":358}]},"start":0,"title_name":"FINAL FANTASY\u00ae III","total_results":0,"depth":0,"skuFound":true}