{"bucket":"games","cloud_only_platform":["NONE"],"container_type":"product","content_type":"1","default_sku":{"amortizeFlag":false,"bundleExclusiveFlag":false,"chargeImmediatelyFlag":false,"charge_type_id":0,"credit_card_required_flag":0,"defaultSku":true,"display_price":"$39.99","eligibilities":[],"entitlements":[{"description":null,"drms":[{"drm_category_type":5,"id":"UP0700-PCSE00595_00-WJ45JSVVSPSV0000","is_streamable":0,"media_prop":[],"size":1732717152,"type":2}],"duration":0,"exp_after_first_use":0,"feature_type_id":0,"id":"UP0700-PCSE00595_00-WJ45JSVVSPSV0000","license_type":1,"name":"J-STARS Victory VS+","packageType":null,"packages":[],"preorder_placeholder_flag":false,"size":0,"subType":0,"subtitle_language_codes":null,"type":2,"use_count":0,"voice_language_codes":null}],"id":"UP0700-PCSE00595_00-WJ45JSVVSPSV0000-U001","is_original":false,"name":"Full Game","platforms":[0,1,10],"price":3999,"rewards":[],"seasonPassExclusiveFlag":false,"skuAvailabilityOverrideFlag":false,"sku_type":0,"type":"standard"},"gameContentTypesList":[{"name":"Game","key":"GAME"}],"game_contentType":"Game","id":"UP0700-PCSE00595_00-WJ45JSVVSPSV0000","images":[{"type":1,"url":"http:\/\/apollo2.dl.playstation.net\/cdn\/UP0700\/PCSE00595_00\/JbhrIffISp553scwhQpczqbuzzuXKU2Z.png"},{"type":2,"url":"http:\/\/apollo2.dl.playstation.net\/cdn\/UP0700\/PCSE00595_00\/zieBW0lxdVtuzwA9QTcBdDZFT29SMHMD.png"},{"type":9,"url":"http:\/\/apollo2.dl.playstation.net\/cdn\/UP0700\/PCSE00595_00\/eL8QUuwr7V3XghWBRu2YuSGaYZcGo6zP.png"},{"type":10,"url":"http:\/\/apollo2.dl.playstation.net\/cdn\/UP0700\/PCSE00595_00\/kk3tQMLuD8vPw7LohtOXJld3AvxFHVl4.png"}],"name":"J-STARS Victory VS+","playable_platform":["PS Vita"],"provider_name":"Bandai Namco Games America Inc.","release_date":"2015-08-04T00:00:00Z","restricted":false,"revision":2,"short_name":"J-STARS Victory VS+","timestamp":1470693877000,"top_category":"downloadable_game","url":"https:\/\/store.playstation.com\/store\/api\/chihiro\/00_09_000\/container\/US\/en\/999\/UP0700-PCSE00595_00-WJ45JSVVSPSV0000?platform=vita&game_content_type=games&size=30&gkb=1&geoCountry=RU&start=0","expanded":true,"age_limit":13,"content_descriptors":[{"description":"Crude Humor","url":null,"name":"Crude Humor"},{"description":"Mild Language","url":null,"name":"Mild Language"},{"description":"Suggestive Themes","url":null,"name":"Suggestive Themes"},{"description":"Online Interactions Not Rated by the ESRB","url":null,"name":"Online Interactions Not Rated by the ESRB"},{"description":"Cartoon Violence","url":null,"name":"Cartoon Violence"}],"content_origin":0,"content_rating":{"rating_system":"ESRB","url":"https:\/\/cdn-a.sonyentertainmentnetwork.com\/grc\/images\/ratings\/hd\/esrb\/t.png"},"dob_required":false,"links":[],"long_desc":"Who is the strongest team amongst the legendary Jump characters? Find out in J-STARS Victory VS+, featuring over 50 characters from 32 different manga series from WEEKLY SHONEN JUMP. Progress through the JUMP World featuring environments recalling NARUTO\u2122, DRAGON BALL Z\u00ae, ONE PIECE and other memorable locations and moments.  Enjoy a grand adventure as your favorite heroes and fight in local and online 2-on-2 versus battles or test your skills in Arcade Mode. Strategically use combination attacks and unleash ultimate attacks using the Voltage Gauge system to best your opponent. It's the ultimate dream for every anime fan!<br><br>Some functions and features may not be available on PlayStation TV.<br><br>1 player(s)<br>Ad Hoc Mode 2-4 Players<br>Network Only 2-4 Players<br>Network Features<br>46080KB Minimum<br>Touchscreen<br>Dual Analog Sticks<br><br>  Software subject to license (us.playstation.com\/softwarelicense).  Online activity subject to Terms of Services and User Agreement (www.playstationnetwork.com\/terms-of-service). One time license fee entitles play on up to 3 PlayStation\u00ae Vita systems activated by this account.<br><br>\u00a9J-STARS VictoryVersus PROJECT<br>Game \u00a92015 BANDAI NAMCO Entertainment Inc.","media_layouts":[{"type":"screenshots","height":1,"width":1},{"type":"description","height":1,"width":3}],"metadata":{"cloud_only_platform":{"name":"cloud_only_platform","values":["NONE"]},"game_genre":{"name":"Genre","values":["ACTION","FIGHTING"]},"playable_platform":{"name":"playable_platform","values":["PS Vita"]},"tertiary_classification":{"name":"tertiary_classification","values":["NA"]},"container_type":{"name":"Container Type","values":["REPRESENTATIVE"]},"genre":{"name":"Genre","values":["Action","Fighting"]},"secondary_classification":{"name":"secondary_classification","values":["GAME"]},"primary_classification":{"name":"primary_classification","values":["PREMIUM_GAME"]}},"pageTypeId":2,"promomedia":[{"anno":"","id":8193,"key":"space","materials":[{"anno":"","countries":[{"agelimit":13,"uagelimit":0,"country":"ar"},{"agelimit":13,"uagelimit":0,"country":"bo"},{"agelimit":13,"uagelimit":0,"country":"br"},{"agelimit":13,"uagelimit":0,"country":"ca"},{"agelimit":13,"uagelimit":0,"country":"cl"},{"agelimit":13,"uagelimit":0,"country":"co"},{"agelimit":13,"uagelimit":0,"country":"cr"},{"agelimit":13,"uagelimit":0,"country":"ec"},{"agelimit":13,"uagelimit":0,"country":"gt"},{"agelimit":13,"uagelimit":0,"country":"hn"},{"agelimit":13,"uagelimit":0,"country":"mx"},{"agelimit":13,"uagelimit":0,"country":"ni"},{"agelimit":13,"uagelimit":0,"country":"pa"},{"agelimit":13,"uagelimit":0,"country":"pe"},{"agelimit":13,"uagelimit":0,"country":"py"},{"agelimit":13,"uagelimit":0,"country":"sv"},{"agelimit":13,"uagelimit":0,"country":"us"},{"agelimit":13,"uagelimit":0,"country":"uy"}],"from":"2015-08-03T00:00:00.000Z","id":1080734184,"lang":["all"],"lastm":"2015-08-03T21:14:11.000Z","until":"2100-12-31T23:59:00.000Z","urls":[{"type":26,"url":"https:\/\/nsx.np.dl.playstation.net\/nsx\/material\/3\/3a5af0319c6ade5b9c8bbd500a809266ba3e6894-1093928.jpg"}]},{"anno":"","countries":[{"agelimit":13,"uagelimit":0,"country":"ar"},{"agelimit":13,"uagelimit":0,"country":"bo"},{"agelimit":13,"uagelimit":0,"country":"br"},{"agelimit":13,"uagelimit":0,"country":"ca"},{"agelimit":13,"uagelimit":0,"country":"cl"},{"agelimit":13,"uagelimit":0,"country":"co"},{"agelimit":13,"uagelimit":0,"country":"cr"},{"agelimit":13,"uagelimit":0,"country":"ec"},{"agelimit":13,"uagelimit":0,"country":"gt"},{"agelimit":13,"uagelimit":0,"country":"hn"},{"agelimit":13,"uagelimit":0,"country":"mx"},{"agelimit":13,"uagelimit":0,"country":"ni"},{"agelimit":13,"uagelimit":0,"country":"pa"},{"agelimit":13,"uagelimit":0,"country":"pe"},{"agelimit":13,"uagelimit":0,"country":"py"},{"agelimit":13,"uagelimit":0,"country":"sv"},{"agelimit":13,"uagelimit":0,"country":"us"},{"agelimit":13,"uagelimit":0,"country":"uy"}],"from":"2015-08-03T00:00:00.000Z","id":1080734183,"lang":["all"],"lastm":"2015-08-03T21:13:37.000Z","until":"2100-12-31T23:59:00.000Z","urls":[{"type":26,"url":"https:\/\/nsx.np.dl.playstation.net\/nsx\/material\/a\/aaa9ad1924b76b1e0a6432aaf39e55dd668ce003-1093927.jpg"}]},{"anno":"","countries":[{"agelimit":13,"uagelimit":0,"country":"ar"},{"agelimit":13,"uagelimit":0,"country":"bo"},{"agelimit":13,"uagelimit":0,"country":"br"},{"agelimit":13,"uagelimit":0,"country":"ca"},{"agelimit":13,"uagelimit":0,"country":"cl"},{"agelimit":13,"uagelimit":0,"country":"co"},{"agelimit":13,"uagelimit":0,"country":"cr"},{"agelimit":13,"uagelimit":0,"country":"ec"},{"agelimit":13,"uagelimit":0,"country":"gt"},{"agelimit":13,"uagelimit":0,"country":"hn"},{"agelimit":13,"uagelimit":0,"country":"mx"},{"agelimit":13,"uagelimit":0,"country":"ni"},{"agelimit":13,"uagelimit":0,"country":"pa"},{"agelimit":13,"uagelimit":0,"country":"pe"},{"agelimit":13,"uagelimit":0,"country":"py"},{"agelimit":13,"uagelimit":0,"country":"sv"},{"agelimit":13,"uagelimit":0,"country":"us"},{"agelimit":13,"uagelimit":0,"country":"uy"}],"from":"2015-08-03T00:00:00.000Z","id":1080734180,"lang":["all"],"lastm":"2015-08-03T21:12:47.000Z","until":"2100-12-31T23:59:00.000Z","urls":[{"type":26,"url":"https:\/\/nsx.np.dl.playstation.net\/nsx\/material\/7\/7d2d01346c3444862b733d6622c3fb40fe39f3c2-1093924.jpg"}]},{"anno":"","countries":[{"agelimit":13,"uagelimit":0,"country":"ar"},{"agelimit":13,"uagelimit":0,"country":"bo"},{"agelimit":13,"uagelimit":0,"country":"br"},{"agelimit":13,"uagelimit":0,"country":"ca"},{"agelimit":13,"uagelimit":0,"country":"cl"},{"agelimit":13,"uagelimit":0,"country":"co"},{"agelimit":13,"uagelimit":0,"country":"cr"},{"agelimit":13,"uagelimit":0,"country":"ec"},{"agelimit":13,"uagelimit":0,"country":"gt"},{"agelimit":13,"uagelimit":0,"country":"hn"},{"agelimit":13,"uagelimit":0,"country":"mx"},{"agelimit":13,"uagelimit":0,"country":"ni"},{"agelimit":13,"uagelimit":0,"country":"pa"},{"agelimit":13,"uagelimit":0,"country":"pe"},{"agelimit":13,"uagelimit":0,"country":"py"},{"agelimit":13,"uagelimit":0,"country":"sv"},{"agelimit":13,"uagelimit":0,"country":"us"},{"agelimit":13,"uagelimit":0,"country":"uy"}],"from":"2015-08-03T00:00:00.000Z","id":1080734179,"lang":["all"],"lastm":"2015-08-03T21:12:20.000Z","until":"2100-12-31T23:59:00.000Z","urls":[{"type":26,"url":"https:\/\/nsx.np.dl.playstation.net\/nsx\/material\/0\/0a357725d9c28a2e9f975a0c2b97ef57511cd65e-1093923.jpg"}]},{"anno":"","countries":[{"agelimit":13,"uagelimit":0,"country":"ar"},{"agelimit":13,"uagelimit":0,"country":"bo"},{"agelimit":13,"uagelimit":0,"country":"br"},{"agelimit":13,"uagelimit":0,"country":"ca"},{"agelimit":13,"uagelimit":0,"country":"cl"},{"agelimit":13,"uagelimit":0,"country":"co"},{"agelimit":13,"uagelimit":0,"country":"cr"},{"agelimit":13,"uagelimit":0,"country":"ec"},{"agelimit":13,"uagelimit":0,"country":"gt"},{"agelimit":13,"uagelimit":0,"country":"hn"},{"agelimit":13,"uagelimit":0,"country":"mx"},{"agelimit":13,"uagelimit":0,"country":"ni"},{"agelimit":13,"uagelimit":0,"country":"pa"},{"agelimit":13,"uagelimit":0,"country":"pe"},{"agelimit":13,"uagelimit":0,"country":"py"},{"agelimit":13,"uagelimit":0,"country":"sv"},{"agelimit":13,"uagelimit":0,"country":"us"},{"agelimit":13,"uagelimit":0,"country":"uy"}],"from":"2015-08-03T00:00:00.000Z","id":1080734178,"lang":["all"],"lastm":"2015-08-03T21:11:53.000Z","until":"2100-12-31T23:59:00.000Z","urls":[{"type":26,"url":"https:\/\/nsx.np.dl.playstation.net\/nsx\/material\/a\/a86b1c9caed6365260a51e4e24ae23f9ed4c76ee-1093922.jpg"}]},{"anno":"","countries":[{"agelimit":13,"uagelimit":0,"country":"ar"},{"agelimit":13,"uagelimit":0,"country":"bo"},{"agelimit":13,"uagelimit":0,"country":"br"},{"agelimit":13,"uagelimit":0,"country":"ca"},{"agelimit":13,"uagelimit":0,"country":"cl"},{"agelimit":13,"uagelimit":0,"country":"co"},{"agelimit":13,"uagelimit":0,"country":"cr"},{"agelimit":13,"uagelimit":0,"country":"ec"},{"agelimit":13,"uagelimit":0,"country":"gt"},{"agelimit":13,"uagelimit":0,"country":"hn"},{"agelimit":13,"uagelimit":0,"country":"mx"},{"agelimit":13,"uagelimit":0,"country":"ni"},{"agelimit":13,"uagelimit":0,"country":"pa"},{"agelimit":13,"uagelimit":0,"country":"pe"},{"agelimit":13,"uagelimit":0,"country":"py"},{"agelimit":13,"uagelimit":0,"country":"sv"},{"agelimit":13,"uagelimit":0,"country":"us"},{"agelimit":13,"uagelimit":0,"country":"uy"}],"from":"2015-08-03T00:00:00.000Z","id":1080734177,"lang":["all"],"lastm":"2015-08-03T21:11:21.000Z","until":"2100-12-31T23:59:00.000Z","urls":[{"type":26,"url":"https:\/\/nsx.np.dl.playstation.net\/nsx\/material\/6\/6aa90d1ffd10c6b31475470c8399902be09fa4bb-1093921.jpg"}]},{"anno":"","countries":[{"agelimit":13,"uagelimit":0,"country":"ar"},{"agelimit":13,"uagelimit":0,"country":"bo"},{"agelimit":13,"uagelimit":0,"country":"br"},{"agelimit":13,"uagelimit":0,"country":"ca"},{"agelimit":13,"uagelimit":0,"country":"cl"},{"agelimit":13,"uagelimit":0,"country":"co"},{"agelimit":13,"uagelimit":0,"country":"cr"},{"agelimit":13,"uagelimit":0,"country":"ec"},{"agelimit":13,"uagelimit":0,"country":"gt"},{"agelimit":13,"uagelimit":0,"country":"hn"},{"agelimit":13,"uagelimit":0,"country":"mx"},{"agelimit":13,"uagelimit":0,"country":"ni"},{"agelimit":13,"uagelimit":0,"country":"pa"},{"agelimit":13,"uagelimit":0,"country":"pe"},{"agelimit":13,"uagelimit":0,"country":"py"},{"agelimit":13,"uagelimit":0,"country":"sv"},{"agelimit":13,"uagelimit":0,"country":"us"},{"agelimit":13,"uagelimit":0,"country":"uy"}],"from":"2015-08-03T00:00:00.000Z","id":1080734176,"lang":["all"],"lastm":"2015-08-03T21:10:56.000Z","until":"2100-12-31T23:59:00.000Z","urls":[{"type":26,"url":"https:\/\/nsx.np.dl.playstation.net\/nsx\/material\/8\/821b8b3f21698e87c1dc87a0e0a9f0ab4737b3f8-1093920.jpg"}]},{"anno":"","countries":[{"agelimit":13,"uagelimit":0,"country":"ar"},{"agelimit":13,"uagelimit":0,"country":"bo"},{"agelimit":13,"uagelimit":0,"country":"br"},{"agelimit":13,"uagelimit":0,"country":"ca"},{"agelimit":13,"uagelimit":0,"country":"cl"},{"agelimit":13,"uagelimit":0,"country":"co"},{"agelimit":13,"uagelimit":0,"country":"cr"},{"agelimit":13,"uagelimit":0,"country":"ec"},{"agelimit":13,"uagelimit":0,"country":"gt"},{"agelimit":13,"uagelimit":0,"country":"hn"},{"agelimit":13,"uagelimit":0,"country":"mx"},{"agelimit":13,"uagelimit":0,"country":"ni"},{"agelimit":13,"uagelimit":0,"country":"pa"},{"agelimit":13,"uagelimit":0,"country":"pe"},{"agelimit":13,"uagelimit":0,"country":"py"},{"agelimit":13,"uagelimit":0,"country":"sv"},{"agelimit":13,"uagelimit":0,"country":"us"},{"agelimit":13,"uagelimit":0,"country":"uy"}],"from":"2015-08-03T00:00:00.000Z","id":1080734175,"lang":["all"],"lastm":"2015-08-03T21:10:26.000Z","until":"2100-12-31T23:59:00.000Z","urls":[{"type":26,"url":"https:\/\/nsx.np.dl.playstation.net\/nsx\/material\/e\/e331128a259d2c954f80c6b7ef884827bc5f8971-1093919.jpg"}]},{"anno":"","countries":[{"agelimit":13,"uagelimit":0,"country":"ar"},{"agelimit":13,"uagelimit":0,"country":"bo"},{"agelimit":13,"uagelimit":0,"country":"br"},{"agelimit":13,"uagelimit":0,"country":"ca"},{"agelimit":13,"uagelimit":0,"country":"cl"},{"agelimit":13,"uagelimit":0,"country":"co"},{"agelimit":13,"uagelimit":0,"country":"cr"},{"agelimit":13,"uagelimit":0,"country":"ec"},{"agelimit":13,"uagelimit":0,"country":"gt"},{"agelimit":13,"uagelimit":0,"country":"hn"},{"agelimit":13,"uagelimit":0,"country":"mx"},{"agelimit":13,"uagelimit":0,"country":"ni"},{"agelimit":13,"uagelimit":0,"country":"pa"},{"agelimit":13,"uagelimit":0,"country":"pe"},{"agelimit":13,"uagelimit":0,"country":"py"},{"agelimit":13,"uagelimit":0,"country":"sv"},{"agelimit":13,"uagelimit":0,"country":"us"},{"agelimit":13,"uagelimit":0,"country":"uy"}],"from":"2015-08-03T00:00:00.000Z","id":1080734174,"lang":["all"],"lastm":"2015-08-03T21:10:02.000Z","until":"2100-12-31T23:59:00.000Z","urls":[{"type":26,"url":"https:\/\/nsx.np.dl.playstation.net\/nsx\/material\/5\/580dfcc12340fbcf727afe43ac6b49650abc84dd-1093918.jpg"}]},{"anno":"","countries":[{"agelimit":13,"uagelimit":0,"country":"ar"},{"agelimit":13,"uagelimit":0,"country":"bo"},{"agelimit":13,"uagelimit":0,"country":"br"},{"agelimit":13,"uagelimit":0,"country":"ca"},{"agelimit":13,"uagelimit":0,"country":"cl"},{"agelimit":13,"uagelimit":0,"country":"co"},{"agelimit":13,"uagelimit":0,"country":"cr"},{"agelimit":13,"uagelimit":0,"country":"ec"},{"agelimit":13,"uagelimit":0,"country":"gt"},{"agelimit":13,"uagelimit":0,"country":"hn"},{"agelimit":13,"uagelimit":0,"country":"mx"},{"agelimit":13,"uagelimit":0,"country":"ni"},{"agelimit":13,"uagelimit":0,"country":"pa"},{"agelimit":13,"uagelimit":0,"country":"pe"},{"agelimit":13,"uagelimit":0,"country":"py"},{"agelimit":13,"uagelimit":0,"country":"sv"},{"agelimit":13,"uagelimit":0,"country":"us"},{"agelimit":13,"uagelimit":0,"country":"uy"}],"from":"2015-08-03T00:00:00.000Z","id":1080734172,"lang":["all"],"lastm":"2015-08-03T21:09:36.000Z","until":"2100-12-31T23:59:00.000Z","urls":[{"type":26,"url":"https:\/\/nsx.np.dl.playstation.net\/nsx\/material\/c\/c429b92fe9ece3c2f4a6f601bd8da51f4c7e9d88-1093916.jpg"}]}],"multi":"ordered","rep":"t","type":99},{"anno":"","id":8196,"key":"space","materials":[{"anno":"","countries":[{"agelimit":13,"uagelimit":0,"country":"ar"},{"agelimit":13,"uagelimit":0,"country":"bo"},{"agelimit":13,"uagelimit":0,"country":"br"},{"agelimit":13,"uagelimit":0,"country":"ca"},{"agelimit":13,"uagelimit":0,"country":"cl"},{"agelimit":13,"uagelimit":0,"country":"co"},{"agelimit":13,"uagelimit":0,"country":"cr"},{"agelimit":13,"uagelimit":0,"country":"ec"},{"agelimit":13,"uagelimit":0,"country":"gt"},{"agelimit":13,"uagelimit":0,"country":"hn"},{"agelimit":13,"uagelimit":0,"country":"mx"},{"agelimit":13,"uagelimit":0,"country":"ni"},{"agelimit":13,"uagelimit":0,"country":"pa"},{"agelimit":13,"uagelimit":0,"country":"pe"},{"agelimit":13,"uagelimit":0,"country":"py"},{"agelimit":13,"uagelimit":0,"country":"sv"},{"agelimit":13,"uagelimit":0,"country":"us"},{"agelimit":13,"uagelimit":0,"country":"uy"}],"from":"2015-08-03T00:00:00.000Z","id":1080734202,"lang":["all"],"lastm":"2015-08-03T22:09:08.000Z","until":"2100-12-31T23:59:00.000Z","urls":[{"type":132,"url":"https:\/\/nsx.np.dl.playstation.net\/nsx\/material\/5\/53ec0257cca91b965f0f3dc3780cfeabcbdf9a61-1093958.png"}]},{"anno":"","countries":[{"agelimit":13,"uagelimit":0,"country":"ar"},{"agelimit":13,"uagelimit":0,"country":"bo"},{"agelimit":13,"uagelimit":0,"country":"br"},{"agelimit":13,"uagelimit":0,"country":"ca"},{"agelimit":13,"uagelimit":0,"country":"cl"},{"agelimit":13,"uagelimit":0,"country":"co"},{"agelimit":13,"uagelimit":0,"country":"cr"},{"agelimit":13,"uagelimit":0,"country":"ec"},{"agelimit":13,"uagelimit":0,"country":"gt"},{"agelimit":13,"uagelimit":0,"country":"hn"},{"agelimit":13,"uagelimit":0,"country":"mx"},{"agelimit":13,"uagelimit":0,"country":"ni"},{"agelimit":13,"uagelimit":0,"country":"pa"},{"agelimit":13,"uagelimit":0,"country":"pe"},{"agelimit":13,"uagelimit":0,"country":"py"},{"agelimit":13,"uagelimit":0,"country":"sv"},{"agelimit":13,"uagelimit":0,"country":"us"},{"agelimit":13,"uagelimit":0,"country":"uy"}],"from":"2015-08-03T00:00:00.000Z","id":1080734201,"lang":["all"],"lastm":"2015-08-03T22:08:31.000Z","until":"2100-12-31T23:59:00.000Z","urls":[{"type":132,"url":"https:\/\/nsx.np.dl.playstation.net\/nsx\/material\/c\/c6914d432ca14f51aeae2659ff40e3b3cca3aebc-1093956.png"}]},{"anno":"","countries":[{"agelimit":13,"uagelimit":0,"country":"ar"},{"agelimit":13,"uagelimit":0,"country":"bo"},{"agelimit":13,"uagelimit":0,"country":"br"},{"agelimit":13,"uagelimit":0,"country":"ca"},{"agelimit":13,"uagelimit":0,"country":"cl"},{"agelimit":13,"uagelimit":0,"country":"co"},{"agelimit":13,"uagelimit":0,"country":"cr"},{"agelimit":13,"uagelimit":0,"country":"ec"},{"agelimit":13,"uagelimit":0,"country":"gt"},{"agelimit":13,"uagelimit":0,"country":"hn"},{"agelimit":13,"uagelimit":0,"country":"mx"},{"agelimit":13,"uagelimit":0,"country":"ni"},{"agelimit":13,"uagelimit":0,"country":"pa"},{"agelimit":13,"uagelimit":0,"country":"pe"},{"agelimit":13,"uagelimit":0,"country":"py"},{"agelimit":13,"uagelimit":0,"country":"sv"},{"agelimit":13,"uagelimit":0,"country":"us"},{"agelimit":13,"uagelimit":0,"country":"uy"}],"from":"2015-08-03T00:00:00.000Z","id":1080734200,"lang":["all"],"lastm":"2015-08-03T22:07:58.000Z","until":"2100-12-31T23:59:00.000Z","urls":[{"type":132,"url":"https:\/\/nsx.np.dl.playstation.net\/nsx\/material\/9\/95a2894d1f21ef3ab8b31bcb17f689e84a334312-1093954.png"}]},{"anno":"","countries":[{"agelimit":13,"uagelimit":0,"country":"ar"},{"agelimit":13,"uagelimit":0,"country":"bo"},{"agelimit":13,"uagelimit":0,"country":"br"},{"agelimit":13,"uagelimit":0,"country":"ca"},{"agelimit":13,"uagelimit":0,"country":"cl"},{"agelimit":13,"uagelimit":0,"country":"co"},{"agelimit":13,"uagelimit":0,"country":"cr"},{"agelimit":13,"uagelimit":0,"country":"ec"},{"agelimit":13,"uagelimit":0,"country":"gt"},{"agelimit":13,"uagelimit":0,"country":"hn"},{"agelimit":13,"uagelimit":0,"country":"mx"},{"agelimit":13,"uagelimit":0,"country":"ni"},{"agelimit":13,"uagelimit":0,"country":"pa"},{"agelimit":13,"uagelimit":0,"country":"pe"},{"agelimit":13,"uagelimit":0,"country":"py"},{"agelimit":13,"uagelimit":0,"country":"sv"},{"agelimit":13,"uagelimit":0,"country":"us"},{"agelimit":13,"uagelimit":0,"country":"uy"}],"from":"2015-08-03T00:00:00.000Z","id":1080734199,"lang":["all"],"lastm":"2015-08-03T22:07:27.000Z","until":"2100-12-31T23:59:00.000Z","urls":[{"type":132,"url":"https:\/\/nsx.np.dl.playstation.net\/nsx\/material\/2\/239bd34110ec3da4ff38d88e71b48667d692e7c1-1093952.png"}]},{"anno":"","countries":[{"agelimit":13,"uagelimit":0,"country":"ar"},{"agelimit":13,"uagelimit":0,"country":"bo"},{"agelimit":13,"uagelimit":0,"country":"br"},{"agelimit":13,"uagelimit":0,"country":"ca"},{"agelimit":13,"uagelimit":0,"country":"cl"},{"agelimit":13,"uagelimit":0,"country":"co"},{"agelimit":13,"uagelimit":0,"country":"cr"},{"agelimit":13,"uagelimit":0,"country":"ec"},{"agelimit":13,"uagelimit":0,"country":"gt"},{"agelimit":13,"uagelimit":0,"country":"hn"},{"agelimit":13,"uagelimit":0,"country":"mx"},{"agelimit":13,"uagelimit":0,"country":"ni"},{"agelimit":13,"uagelimit":0,"country":"pa"},{"agelimit":13,"uagelimit":0,"country":"pe"},{"agelimit":13,"uagelimit":0,"country":"py"},{"agelimit":13,"uagelimit":0,"country":"sv"},{"agelimit":13,"uagelimit":0,"country":"us"},{"agelimit":13,"uagelimit":0,"country":"uy"}],"from":"2015-08-03T00:00:00.000Z","id":1080734198,"lang":["all"],"lastm":"2015-08-03T22:05:54.000Z","until":"2100-12-31T23:59:00.000Z","urls":[{"type":132,"url":"https:\/\/nsx.np.dl.playstation.net\/nsx\/material\/2\/20eb37c7d764a90f3db29e83ebda2df0f71389ab-1093951.png"}]},{"anno":"","countries":[{"agelimit":13,"uagelimit":0,"country":"ar"},{"agelimit":13,"uagelimit":0,"country":"bo"},{"agelimit":13,"uagelimit":0,"country":"br"},{"agelimit":13,"uagelimit":0,"country":"ca"},{"agelimit":13,"uagelimit":0,"country":"cl"},{"agelimit":13,"uagelimit":0,"country":"co"},{"agelimit":13,"uagelimit":0,"country":"cr"},{"agelimit":13,"uagelimit":0,"country":"ec"},{"agelimit":13,"uagelimit":0,"country":"gt"},{"agelimit":13,"uagelimit":0,"country":"hn"},{"agelimit":13,"uagelimit":0,"country":"mx"},{"agelimit":13,"uagelimit":0,"country":"ni"},{"agelimit":13,"uagelimit":0,"country":"pa"},{"agelimit":13,"uagelimit":0,"country":"pe"},{"agelimit":13,"uagelimit":0,"country":"py"},{"agelimit":13,"uagelimit":0,"country":"sv"},{"agelimit":13,"uagelimit":0,"country":"us"},{"agelimit":13,"uagelimit":0,"country":"uy"}],"from":"2015-08-03T00:00:00.000Z","id":1080734197,"lang":["all"],"lastm":"2015-08-03T22:04:51.000Z","until":"2100-12-31T23:59:00.000Z","urls":[{"type":132,"url":"https:\/\/nsx.np.dl.playstation.net\/nsx\/material\/0\/053f3283318d784cba74f2e4c930e638a11a8be2-1093949.png"}]},{"anno":"","countries":[{"agelimit":13,"uagelimit":0,"country":"ar"},{"agelimit":13,"uagelimit":0,"country":"bo"},{"agelimit":13,"uagelimit":0,"country":"br"},{"agelimit":13,"uagelimit":0,"country":"ca"},{"agelimit":13,"uagelimit":0,"country":"cl"},{"agelimit":13,"uagelimit":0,"country":"co"},{"agelimit":13,"uagelimit":0,"country":"cr"},{"agelimit":13,"uagelimit":0,"country":"ec"},{"agelimit":13,"uagelimit":0,"country":"gt"},{"agelimit":13,"uagelimit":0,"country":"hn"},{"agelimit":13,"uagelimit":0,"country":"mx"},{"agelimit":13,"uagelimit":0,"country":"ni"},{"agelimit":13,"uagelimit":0,"country":"pa"},{"agelimit":13,"uagelimit":0,"country":"pe"},{"agelimit":13,"uagelimit":0,"country":"py"},{"agelimit":13,"uagelimit":0,"country":"sv"},{"agelimit":13,"uagelimit":0,"country":"us"},{"agelimit":13,"uagelimit":0,"country":"uy"}],"from":"2015-08-03T00:00:00.000Z","id":1080734196,"lang":["all"],"lastm":"2015-08-03T22:03:46.000Z","until":"2100-12-31T23:59:00.000Z","urls":[{"type":132,"url":"https:\/\/nsx.np.dl.playstation.net\/nsx\/material\/b\/b4669705dbba1909b8692a43be3f03aa7502fca9-1093947.png"}]},{"anno":"","countries":[{"agelimit":13,"uagelimit":0,"country":"ar"},{"agelimit":13,"uagelimit":0,"country":"bo"},{"agelimit":13,"uagelimit":0,"country":"br"},{"agelimit":13,"uagelimit":0,"country":"ca"},{"agelimit":13,"uagelimit":0,"country":"cl"},{"agelimit":13,"uagelimit":0,"country":"co"},{"agelimit":13,"uagelimit":0,"country":"cr"},{"agelimit":13,"uagelimit":0,"country":"ec"},{"agelimit":13,"uagelimit":0,"country":"gt"},{"agelimit":13,"uagelimit":0,"country":"hn"},{"agelimit":13,"uagelimit":0,"country":"mx"},{"agelimit":13,"uagelimit":0,"country":"ni"},{"agelimit":13,"uagelimit":0,"country":"pa"},{"agelimit":13,"uagelimit":0,"country":"pe"},{"agelimit":13,"uagelimit":0,"country":"py"},{"agelimit":13,"uagelimit":0,"country":"sv"},{"agelimit":13,"uagelimit":0,"country":"us"},{"agelimit":13,"uagelimit":0,"country":"uy"}],"from":"2015-08-03T00:00:00.000Z","id":1080734195,"lang":["all"],"lastm":"2015-08-03T22:03:06.000Z","until":"2100-12-31T23:59:00.000Z","urls":[{"type":132,"url":"https:\/\/nsx.np.dl.playstation.net\/nsx\/material\/5\/56d99a8beced4158187c05f186cbf053119c5a50-1093946.png"}]},{"anno":"","countries":[{"agelimit":13,"uagelimit":0,"country":"ar"},{"agelimit":13,"uagelimit":0,"country":"bo"},{"agelimit":13,"uagelimit":0,"country":"br"},{"agelimit":13,"uagelimit":0,"country":"ca"},{"agelimit":13,"uagelimit":0,"country":"cl"},{"agelimit":13,"uagelimit":0,"country":"co"},{"agelimit":13,"uagelimit":0,"country":"cr"},{"agelimit":13,"uagelimit":0,"country":"ec"},{"agelimit":13,"uagelimit":0,"country":"gt"},{"agelimit":13,"uagelimit":0,"country":"hn"},{"agelimit":13,"uagelimit":0,"country":"mx"},{"agelimit":13,"uagelimit":0,"country":"ni"},{"agelimit":13,"uagelimit":0,"country":"pa"},{"agelimit":13,"uagelimit":0,"country":"pe"},{"agelimit":13,"uagelimit":0,"country":"py"},{"agelimit":13,"uagelimit":0,"country":"sv"},{"agelimit":13,"uagelimit":0,"country":"us"},{"agelimit":13,"uagelimit":0,"country":"uy"}],"from":"2015-08-03T00:00:00.000Z","id":1080734194,"lang":["all"],"lastm":"2015-08-03T22:02:31.000Z","until":"2100-12-31T23:59:00.000Z","urls":[{"type":132,"url":"https:\/\/nsx.np.dl.playstation.net\/nsx\/material\/d\/dc9ea3cb56678a82011f40b3702a4a492a4f3a20-1093945.png"}]},{"anno":"","countries":[{"agelimit":13,"uagelimit":0,"country":"ar"},{"agelimit":13,"uagelimit":0,"country":"bo"},{"agelimit":13,"uagelimit":0,"country":"br"},{"agelimit":13,"uagelimit":0,"country":"ca"},{"agelimit":13,"uagelimit":0,"country":"cl"},{"agelimit":13,"uagelimit":0,"country":"co"},{"agelimit":13,"uagelimit":0,"country":"cr"},{"agelimit":13,"uagelimit":0,"country":"ec"},{"agelimit":13,"uagelimit":0,"country":"gt"},{"agelimit":13,"uagelimit":0,"country":"hn"},{"agelimit":13,"uagelimit":0,"country":"mx"},{"agelimit":13,"uagelimit":0,"country":"ni"},{"agelimit":13,"uagelimit":0,"country":"pa"},{"agelimit":13,"uagelimit":0,"country":"pe"},{"agelimit":13,"uagelimit":0,"country":"py"},{"agelimit":13,"uagelimit":0,"country":"sv"},{"agelimit":13,"uagelimit":0,"country":"us"},{"agelimit":13,"uagelimit":0,"country":"uy"}],"from":"2015-08-03T00:00:00.000Z","id":1080734193,"lang":["all"],"lastm":"2015-08-03T22:01:42.000Z","until":"2100-12-31T23:59:00.000Z","urls":[{"type":132,"url":"https:\/\/nsx.np.dl.playstation.net\/nsx\/material\/a\/af58df86fe06e20ceb5c41b753f7f86a097b6309-1093944.png"}]}],"multi":"ordered","rep":"t","type":99}],"size":0,"sku_links":[],"skus":[{"amortizeFlag":false,"bundleExclusiveFlag":false,"chargeImmediatelyFlag":false,"charge_type_id":0,"credit_card_required_flag":0,"defaultSku":true,"display_price":"$39.99","eligibilities":[],"entitlements":[{"description":null,"drms":[{"drm_category_type":5,"id":"UP0700-PCSE00595_00-WJ45JSVVSPSV0000","is_streamable":0,"media_prop":[],"size":1732717152,"type":2}],"duration":0,"exp_after_first_use":0,"feature_type_id":0,"id":"UP0700-PCSE00595_00-WJ45JSVVSPSV0000","license_type":1,"name":"J-STARS Victory VS+","packageType":null,"packages":[],"preorder_placeholder_flag":false,"size":0,"subType":0,"subtitle_language_codes":null,"type":2,"use_count":0,"voice_language_codes":null}],"id":"UP0700-PCSE00595_00-WJ45JSVVSPSV0000-U001","is_original":false,"name":"Full Game","platforms":[0,1,10],"price":3999,"rewards":[],"seasonPassExclusiveFlag":false,"skuAvailabilityOverrideFlag":false,"sku_type":0,"type":"standard"}],"star_rating":{"total":"824","score":"4.73","count":[{"star":1,"count":11},{"star":2,"count":10},{"star":3,"count":33},{"star":4,"count":75},{"star":5,"count":695}]},"start":0,"title_name":"J-STARS Victory VS+","total_results":0,"depth":0,"skuFound":true}