{"bucket":"games","container_type":"product","content_type":"1","default_sku":{"amortizeFlag":false,"bundleExclusiveFlag":false,"chargeImmediatelyFlag":false,"charge_type_id":0,"credit_card_required_flag":0,"defaultSku":true,"display_price":"$14.99","eligibilities":[],"entitlements":[{"description":null,"drms":[{"drm_category_type":1,"id":"UP9000-UCUS98751_00-0000000000000001","is_streamable":0,"media_prop":[],"size":397972896,"type":2}],"duration":0,"exp_after_first_use":0,"feature_type_id":0,"id":"UP9000-UCUS98751_00-0000000000000001","license_type":1,"name":"Patapon\u00ae 3","packageType":null,"packages":[],"preorder_placeholder_flag":false,"size":0,"subType":0,"subtitle_language_codes":null,"type":2,"use_count":0,"voice_language_codes":null},{"description":null,"drms":[{"drm_category_type":1,"id":"UP9000-NPUG30071_00-PATAPONDIGIGUIDE","is_streamable":0,"media_prop":[],"size":246790928,"type":2}],"duration":0,"exp_after_first_use":0,"feature_type_id":0,"id":"UP9000-NPUG30071_00-PATAPONDIGIGUIDE","license_type":1,"name":"Patapon\u00ae 3 Digital Guide","packageType":null,"packages":[],"preorder_placeholder_flag":false,"size":0,"subType":0,"subtitle_language_codes":null,"type":2,"use_count":0,"voice_language_codes":null},{"description":null,"drms":[],"duration":0,"exp_after_first_use":0,"feature_type_id":0,"id":"UP9000-UCUS98751_00-DLL001","license_type":0,"name":"Patapon\u00ae 3 Online Entitlement","packageType":null,"packages":[],"preorder_placeholder_flag":false,"size":0,"subType":0,"subtitle_language_codes":null,"type":1,"use_count":0,"voice_language_codes":null}],"id":"UP9000-UCUS98751_00-0000000000000001-U002","is_original":false,"name":"616 MB Required","platforms":[0,1,10],"price":1499,"rewards":[{"id":"IP9101-NPIA90005_01-RWD-974","entitlement_id":"IP9101-NPIA90005_01-RWD-974","service_provider_id":"IP9101","discount":100,"price":0,"reward_type":2,"display_price":"Free","name":"SP Discount\/ Sub Ends; 100% off","description":"<b><font color=\"#FDD017\">This item is available as a free download for PlayStation\u00aePlus users.<\/font><\/b>","isPlus":true,"start_date":"2016-08-02T15:00:00Z","end_date":"2016-09-06T15:00:00Z","reward_source_type_id":1}],"seasonPassExclusiveFlag":false,"skuAvailabilityOverrideFlag":false,"sku_type":0,"type":"standard"},"gameContentTypesList":[{"name":"Game","key":"GAME"}],"game_contentType":"Game","id":"UP9000-UCUS98751_00-0000000000000001","images":[{"type":1,"url":"http:\/\/apollo2.dl.playstation.net\/cdn\/UP9000\/UCUS98751_00\/AphtKzJEfTqPvHgwDnpofKnsYGWURYnk.png"},{"type":2,"url":"http:\/\/apollo2.dl.playstation.net\/cdn\/UP9000\/UCUS98751_00\/HrfIOQCGBWxwaxvrfiRNwFesDPcYkqtI.png"},{"type":9,"url":"http:\/\/apollo2.dl.playstation.net\/cdn\/UP9000\/UCUS98751_00\/AphtKzJEfTqPvHgwDnpofKnsYGWURYnk_160.png"}],"name":"Patapon\u00ae 3","playable_platform":["PSP","PS Vita"],"provider_name":"Sony Interactive Entertainment America","release_date":"2011-04-12T00:00:00Z","restricted":false,"revision":21,"short_name":"Patapon\u00ae 3","timestamp":1470853295000,"top_category":"downloadable_game","url":"https:\/\/store.playstation.com\/store\/api\/chihiro\/00_09_000\/container\/US\/en\/999\/UP9000-UCUS98751_00-0000000000000001?platform=vita&game_content_type=games&size=30&gkb=1&geoCountry=RU&start=0","expanded":true,"age_limit":6,"attributes":{"facets":[],"next":[]},"content_descriptors":[{"description":"Mild Cartoon Violence","url":null,"name":"Mild Cartoon Violence"},{"description":"Comic Mischief","url":null,"name":"Comic Mischief"},{"description":"Online Interactions Not Rated by the ESRB","url":null,"name":"Online Interactions Not Rated by the ESRB"}],"content_origin":0,"content_rating":{"rating_system":"ESRB","url":"https:\/\/store.playstation.com\/store\/api\/chihiro\/00_09_000\/images\/ratings\/games\/esrb_rating_US_E.jpg"},"dob_required":false,"links":[],"long_desc":"Now playable on your PS Vita*\r\n<BR>\r\n<BR>The critically-acclaimed rhythm-based adventure game is now available offering new quests, increased customization and all-new online battles. Play the campaign with your friends, go head-to-head, or take on a clan of other Patapon gamers with network play for up to eight people. You can also customize your tribe with different weapons and abilities before you head into battle in the greatest portable adventure of rhythm and war.\r\n<BR>\r\n<BR>*Certain limitations apply to Wi-Fi connectivity.  Player responsible for Wi-Fi fees.\r\n<BR><BR>For wireless play, this game may not be compatible with the UMD disc version of the game.<BR><BR>This item is being licensed to you by Sony Computer Entertainment America and is subject to the Network Terms of Service and User Agreement, this item\u2019s use restrictions and other applicable terms located at www.us.playstation.com\/support\/useragreements. If you do not wish to accept all these terms, do not download this item.<BR><BR>Patapon is a registered trademark of Sony Computer Entertainment Inc. \u00a9 2011 Sony Computer Entertainment Inc. \u00a9 2011 Rolito\/Interlink<BR>Use of this item is subject to the PlayStation\u00aeNetwork Terms of Service\/User Agreement. If you do not wish to accept these terms, do not use this item.","media_layouts":[{"type":"description","height":1,"width":4}],"metadata":{"game_genre":{"name":"Genre","values":["MUSIC\/RHYTHM","ROLE_PLAYING_GAMES","STRATEGY"]},"playable_platform":{"name":"playable_platform","values":["PSP","PS Vita"]},"tertiary_classification":{"name":"tertiary_classification","values":["NA"]},"container_type":{"name":"Container Type","values":["REPRESENTATIVE"]},"genre":{"name":"Genre","values":["MUSIC\/RHYTHM","Role-Playing Games (RPG)","Strategy"]},"secondary_classification":{"name":"secondary_classification","values":["GAME"]},"primary_classification":{"name":"primary_classification","values":["PREMIUM_GAME"]}},"pageTypeId":2,"promomedia":[{"anno":"","id":8194,"key":"space","materials":[{"anno":"","countries":[{"agelimit":0,"uagelimit":0,"country":"ca"},{"agelimit":0,"uagelimit":0,"country":"mx"},{"agelimit":0,"uagelimit":0,"country":"us"}],"data":[{"type":29,"name":"928ed60cc4037fabc1215f91ff3cea283c09cd18-77050.txt","data":"VGhpcyBpdGVtIGlzIGF2YWlsYWJsZSBhcyBhIGZyZWUgZG93bmxvYWQgZm9yIFBsYXlTdGF0aW9uwq5QbHVzIHVzZXJzLiBZb3Ugd2lsbCBiZSBhYmxlIHRvIHVzZSB0aGlzIGl0ZW0gYXMgbG9uZyBhcyB5b3UgcmVtYWluIGEgUGxheVN0YXRpb27CrlBsdXMgc3Vic2NyaWJlci4gSWYgeW91ciBQbGF5U3RhdGlvbsKuUGx1cyBzdWJzY3JpcHRpb24gZW5kcywgeW91IHdpbGwgbm8gbG9uZ2VyIGJlIGFibGUgdG8gdXNlIHRoaXMgaXRlbS4gSWYgeW91IHB1cmNoYXNlIGFkZC1vbiBpdGVtcyBmb3IgdXNlIHdpdGggZ2FtZXMgb2J0YWluZWQgZm9yIGZyZWUgdGhyb3VnaCBhIFBsYXlTdGF0aW9uwq5QbHVzIG9mZmVyLCB0aG9zZSBhZGQtb24gaXRlbXMgd2lsbCBvbmx5IGJlIHVzYWJsZSBhcyBsb25nIGFzIHRoZSBnYW1lIGlzIHVzYWJsZS4gSWYgdGhlIGdhbWUgaXMgbm8gbG9uZ2VyIHVzYWJsZSBiZWNhdXNlIHlvdSBhcmUgbm8gbG9uZ2VyIGEgUGxheVN0YXRpb27CrlBsdXMgc3Vic2NyaWJlciwgYSBzZXBhcmF0ZSBwdXJjaGFzZSBvZiB0aGUgZ2FtZSB3aWxsIGJlIHJlcXVpcmVkIGluIG9yZGVyIHRvIHVzZSB0aGUgYWRkLW9uIGl0ZW1zIHlvdSBwdXJjaGFzZWQu"}],"desc":"","from":"2008-01-01T00:00:00.000Z","id":1080454145,"lang":["1"],"lastm":"2010-06-28T22:45:02.000Z","name":"","owner":"","until":"2050-01-01T00:00:00.000Z"}],"multi":"ordered","rep":"t","type":99}],"size":0,"sku_links":[],"skus":[{"amortizeFlag":false,"bundleExclusiveFlag":false,"chargeImmediatelyFlag":false,"charge_type_id":0,"credit_card_required_flag":0,"defaultSku":true,"display_price":"$14.99","eligibilities":[],"entitlements":[{"description":null,"drms":[{"drm_category_type":1,"id":"UP9000-UCUS98751_00-0000000000000001","is_streamable":0,"media_prop":[],"size":397972896,"type":2}],"duration":0,"exp_after_first_use":0,"feature_type_id":0,"id":"UP9000-UCUS98751_00-0000000000000001","license_type":1,"name":"Patapon\u00ae 3","packageType":null,"packages":[],"preorder_placeholder_flag":false,"size":0,"subType":0,"subtitle_language_codes":null,"type":2,"use_count":0,"voice_language_codes":null},{"description":null,"drms":[{"drm_category_type":1,"id":"UP9000-NPUG30071_00-PATAPONDIGIGUIDE","is_streamable":0,"media_prop":[],"size":246790928,"type":2}],"duration":0,"exp_after_first_use":0,"feature_type_id":0,"id":"UP9000-NPUG30071_00-PATAPONDIGIGUIDE","license_type":1,"name":"Patapon\u00ae 3 Digital Guide","packageType":null,"packages":[],"preorder_placeholder_flag":false,"size":0,"subType":0,"subtitle_language_codes":null,"type":2,"use_count":0,"voice_language_codes":null},{"description":null,"drms":[],"duration":0,"exp_after_first_use":0,"feature_type_id":0,"id":"UP9000-UCUS98751_00-DLL001","license_type":0,"name":"Patapon\u00ae 3 Online Entitlement","packageType":null,"packages":[],"preorder_placeholder_flag":false,"size":0,"subType":0,"subtitle_language_codes":null,"type":1,"use_count":0,"voice_language_codes":null}],"id":"UP9000-UCUS98751_00-0000000000000001-U002","is_original":false,"name":"616 MB Required","platforms":[0,1,10],"price":1499,"rewards":[{"id":"IP9101-NPIA90005_01-RWD-974","entitlement_id":"IP9101-NPIA90005_01-RWD-974","service_provider_id":"IP9101","discount":100,"price":0,"reward_type":2,"display_price":"Free","name":"SP Discount\/ Sub Ends; 100% off","description":"<b><font color=\"#FDD017\">This item is available as a free download for PlayStation\u00aePlus users.<\/font><\/b>","isPlus":true,"start_date":"2016-08-02T15:00:00Z","end_date":"2016-09-06T15:00:00Z","reward_source_type_id":1}],"seasonPassExclusiveFlag":false,"skuAvailabilityOverrideFlag":false,"sku_type":0,"type":"standard"}],"sort":"static","star_rating":{"total":"1004","score":"4.82","count":[{"star":1,"count":20},{"star":2,"count":5},{"star":3,"count":18},{"star":4,"count":44},{"star":5,"count":917}]},"start":0,"title_name":"Patapon\u00ae 3","total_results":0,"depth":0,"skuFound":true}